momblish/__init__.py
momblish/cli.py
momblish/corpus.py
momblish/corpus_analyzer.py
momblish/momblish.py
momblish-0.0.1.dist-info/AUTHORS.rst
momblish-0.0.1.dist-info/LICENSE.txt
momblish-0.0.1.dist-info/METADATA
momblish-0.0.1.dist-info/WHEEL
momblish-0.0.1.dist-info/entry_points.txt
momblish-0.0.1.dist-info/top_level.txt
momblish-0.0.1.dist-info/RECORD
