Metadata-Version: 2.1
Name: momblish
Version: 0.0.1
Summary: Generate nonsense words in any language by corpus analysis
Home-page: https://github.com/CypherpunkArmory/mumblish
Author: Stephen Prater
Author-email: me@stephenprater.com
License: mit
Platform: any
Classifier: Development Status :: 4 - Beta
Classifier: Programming Language :: Python
Provides-Extra: testing
Requires-Dist: pytest ; extra == 'testing'
Requires-Dist: pytest-cov ; extra == 'testing'
